regps/__init__.py
regps/_modidx.py
regps/date_compare.py
regps/exif_explorer.py
regps/json_explorer.py
regps/regps.py
regps-0.3.0.dist-info/LICENSE
regps-0.3.0.dist-info/WHEEL
regps-0.3.0.dist-info/METADATA
regps-0.3.0.dist-info/RECORD
