Metadata-Version: 2.1
Name: regps
Version: 0.3.0
Summary: 
Author: mcgillij
Author-email: mcgillivray.jason@gmail.com
Requires-Python: >=3.10,<4.0
Classifier: Programming Language :: Python :: 3
Classifier: Programming Language :: Python :: 3.10
Requires-Dist: ExifRead (>=3.0.0,<4.0.0)
Requires-Dist: Pillow (>=9.2.0,<10.0.0)
Requires-Dist: exif (>=1.3.5,<2.0.0)
Requires-Dist: gpsphoto (>=2.2.3,<3.0.0)
Requires-Dist: piexif (>=1.1.3,<2.0.0)
